mlpackages/LogisticRegression.py
mlpackages/__init__.py
mlpackages/knn.py
mlpackages/linear_svm.py
tests/__init__.py
tests/test_knn.py
tests/test_linear_svm.py
tests/test_logistic_regression.py
ml_packages-1.0.dist-info/METADATA
ml_packages-1.0.dist-info/WHEEL
ml_packages-1.0.dist-info/top_level.txt
ml_packages-1.0.dist-info/RECORD
