Metadata-Version: 2.1
Name: ml-packages
Version: 1.0
Summary: A package for Logistic Regression, KNN, and Decision Linear SVM
Home-page: https://github.com/kam-999/ml-packages.git
Author: kamal
Author-email: kamalar710@gmail.com
Requires-Dist: numpy
